CHANGES.rst
MANIFEST.in
README.rst
buildout.cfg
minitage.cfg
setup.cfg
setup.py
src/minitage/__init__.py
src/minitage.recipe.printer.egg-info/PKG-INFO
src/minitage.recipe.printer.egg-info/SOURCES.txt
src/minitage.recipe.printer.egg-info/dependency_links.txt
src/minitage.recipe.printer.egg-info/entry_points.txt
src/minitage.recipe.printer.egg-info/namespace_packages.txt
src/minitage.recipe.printer.egg-info/not-zip-safe
src/minitage.recipe.printer.egg-info/requires.txt
src/minitage.recipe.printer.egg-info/top_level.txt
src/minitage/recipe/__init__.py
src/minitage/recipe/printer/__init__.py
src/minitage/recipe/printer/printer.py
src/minitage/recipe/printer/tests/__init__.py
src/minitage/recipe/printer/tests/printer.txt
src/minitage/recipe/printer/tests/tests.py